tno.mpc.mpyc.matrix_inverse-0.4.3-py3.8-nspkg.pth
tno/mpc/mpyc/matrix_inverse/__init__.py
tno/mpc/mpyc/matrix_inverse/matrix_inverse.py
tno/mpc/mpyc/matrix_inverse/py.typed
tno/mpc/mpyc/matrix_inverse/test/__init__.py
tno/mpc/mpyc/matrix_inverse/test/test_inverse.py
tno.mpc.mpyc.matrix_inverse-0.4.3.dist-info/LICENSE
tno.mpc.mpyc.matrix_inverse-0.4.3.dist-info/METADATA
tno.mpc.mpyc.matrix_inverse-0.4.3.dist-info/WHEEL
tno.mpc.mpyc.matrix_inverse-0.4.3.dist-info/namespace_packages.txt
tno.mpc.mpyc.matrix_inverse-0.4.3.dist-info/top_level.txt
tno.mpc.mpyc.matrix_inverse-0.4.3.dist-info/RECORD
