Metadata-Version: 2.1
Name: tno.mpc.mpyc.matrix-inverse
Version: 0.4.3
Summary: A generic extension to MPyC that allows you to securely compute the inverse of a matrix that may contain SecFxp values
Home-page: https://mpc.tno.nl/
Author: TNO MPC Lab
Author-email: mpclab@tno.nl
Maintainer: TNO MPC Lab
Maintainer-email: mpclab@tno.nl
License: Apache License, Version 2.0
Download-URL: https://pypi.org/project/tno.mpc.mpyc.matrix_inverse/#files
Project-URL: Documentation, https://docs.mpc.tno.nl/mpyc/matrix_inverse/0.4.3
Project-URL: Source Code, https://github.com/TNO-MPC/mpyc.matrix_inverse
Keywords: TNO,MPC,multi-party computation,MPyC,matrix_inverse
Platform: any
Classifier: License :: OSI Approved :: Apache Software License
Classifier: Programming Language :: Python :: 3
Classifier: Operating System :: OS Independent
Classifier: Intended Audience :: Developers
Classifier: Intended Audience :: Information Technology
Classifier: Intended Audience :: Science/Research
Classifier: Typing :: Typed
Classifier: Topic :: Security :: Cryptography
License-File: LICENSE
Requires-Dist: mpyc (~=0.7.0)
Requires-Dist: numpy
Requires-Dist: tno.mpc.mpyc.stubs (>=0.2.0)
Provides-Extra: gmpy
Requires-Dist: gmpy2 (>=2.1.0) ; extra == 'gmpy'
Provides-Extra: tests
Requires-Dist: pytest ; extra == 'tests'
Requires-Dist: pytest-asyncio ; extra == 'tests'
